cv_pom/__init__.py
cv_pom/cv_pom.py
cv_pom/cv_pom_driver.py
cv_pom/frameworks/__init__.py
cv_pom/frameworks/adb.py
cv_pom/frameworks/os_gui.py
cv_pom/frameworks/printer_driver.py
cv_pom/frameworks/testui.py
cv_pom-0.2.3.dist-info/licenses/LICENSE
cv_pom-0.2.3.dist-info/METADATA
cv_pom-0.2.3.dist-info/WHEEL
cv_pom-0.2.3.dist-info/top_level.txt
cv_pom-0.2.3.dist-info/RECORD
