Metadata-Version: 2.4
Name: cv_pom
Version: 0.2.3
Summary: CV POM
Author-email: Álvaro Santos Laserna López <alvaro.laserna@testdevlab.com>, Arnis Gustins <arnis.gustins@testdevlab.com>
Project-URL: Homepage, https://github.com/testdevlab/cv_pom
Classifier: Programming Language :: Python :: 3
Requires-Python: >=3.9
License-File: LICENSE
Requires-Dist: yolo5
Requires-Dist: opencv-python
Requires-Dist: fastapi
Requires-Dist: pydantic
Requires-Dist: uvicorn
Requires-Dist: ultralytics
Requires-Dist: easyocr
Dynamic: license-file
